README.rst
setup.py
randomlogo/__init__.py
randomlogo.egg-info/PKG-INFO
randomlogo.egg-info/SOURCES.txt
randomlogo.egg-info/dependency_links.txt
randomlogo.egg-info/entry_points.txt
randomlogo.egg-info/requires.txt
randomlogo.egg-info/top_level.txt
randomlogo/templates/escudos.jinja2