Metadata-Version: 1.0
Name: randomlogo
Version: 0.0.1
Summary: Random Logo Generator
Home-page: http://github.com/MSA-Argentina/randomlogo
Author: Felipe Lerena
Author-email: felipelerena@gmail.com
License: LICENSE.txt
Platform: UNKNOWN
